Workbook

Sheet Assumptions
A1: Driver | B1: Value
A2: ListPrice | B2: 49
A3: MoMGrowth | B3: 0.08
A4: Churn | B4: 0.02
A5: COGS% | B5: 0.22
A6: MonthlyOpEx | B6: 85000
A7: TaxRate | B7: 0.21
A8: SeatsPerAcct | B8: 12
A9: Discount | B9: 0.1
A10: SupportCost | B10: 4.5
A11: MarketingPct | B11: 0.12
A12: TargetMargin | B12: 0.55
A14: Acme SaaS FY2026 — edit B2:B5 in the YC demo

Sheet Regions
A1: Region | B1: Jan | C1: Feb | D1: Mar | E1: Apr | F1: May | G1: Jun | H1: Jul | I1: Aug | J1: Sep | K1: Oct | L1: Nov | M1: Dec
A2: Americas | B2: 1200 | C2: =B2*(1+Assumptions!$B$3) | D2: =C2*(1+Assumptions!$B$3) | E2: =D2*(1+Assumptions!$B$3) | F2: =E2*(1+Assumptions!$B$3) | G2: =F2*(1+Assumptions!$B$3) | H2: =G2*(1+Assumptions!$B$3) | I2: =H2*(1+Assumptions!$B$3) | J2: =I2*(1+Assumptions!$B$3) | ... M2: =L2*(1+Assumptions!$B$3)
A3: EMEA | B3: 960 | C3: =B3*(1+Assumptions!$B$3) | D3: =C3*(1+Assumptions!$B$3) | E3: =D3*(1+Assumptions!$B$3) | F3: =E3*(1+Assumptions!$B$3) | G3: =F3*(1+Assumptions!$B$3) | H3: =G3*(1+Assumptions!$B$3) | I3: =H3*(1+Assumptions!$B$3) | J3: =I3*(1+Assumptions!$B$3) | ... M3: =L3*(1+Assumptions!$B$3)
A4: APAC | B4: 800 | C4: =B4*(1+Assumptions!$B$3) | D4: =C4*(1+Assumptions!$B$3) | E4: =D4*(1+Assumptions!$B$3) | F4: =E4*(1+Assumptions!$B$3) | G4: =F4*(1+Assumptions!$B$3) | H4: =G4*(1+Assumptions!$B$3) | I4: =H4*(1+Assumptions!$B$3) | J4: =I4*(1+Assumptions!$B$3) | ... M4: =L4*(1+Assumptions!$B$3)
A5: LATAM | B5: 400 | C5: =B5*(1+Assumptions!$B$3) | D5: =C5*(1+Assumptions!$B$3) | E5: =D5*(1+Assumptions!$B$3) | F5: =E5*(1+Assumptions!$B$3) | G5: =F5*(1+Assumptions!$B$3) | H5: =G5*(1+Assumptions!$B$3) | I5: =H5*(1+Assumptions!$B$3) | J5: =I5*(1+Assumptions!$B$3) | ... M5: =L5*(1+Assumptions!$B$3)
A6: ANZ | B6: 320 | C6: =B6*(1+Assumptions!$B$3) | D6: =C6*(1+Assumptions!$B$3) | E6: =D6*(1+Assumptions!$B$3) | F6: =E6*(1+Assumptions!$B$3) | G6: =F6*(1+Assumptions!$B$3) | H6: =G6*(1+Assumptions!$B$3) | I6: =H6*(1+Assumptions!$B$3) | J6: =I6*(1+Assumptions!$B$3) | ... M6: =L6*(1+Assumptions!$B$3)
A7: India | B7: 560 | C7: =B7*(1+Assumptions!$B$3) | D7: =C7*(1+Assumptions!$B$3) | E7: =D7*(1+Assumptions!$B$3) | F7: =E7*(1+Assumptions!$B$3) | G7: =F7*(1+Assumptions!$B$3) | H7: =G7*(1+Assumptions!$B$3) | I7: =H7*(1+Assumptions!$B$3) | J7: =I7*(1+Assumptions!$B$3) | ... M7: =L7*(1+Assumptions!$B$3)
A8: Japan | B8: 640 | C8: =B8*(1+Assumptions!$B$3) | D8: =C8*(1+Assumptions!$B$3) | E8: =D8*(1+Assumptions!$B$3) | F8: =E8*(1+Assumptions!$B$3) | G8: =F8*(1+Assumptions!$B$3) | H8: =G8*(1+Assumptions!$B$3) | I8: =H8*(1+Assumptions!$B$3) | J8: =I8*(1+Assumptions!$B$3) | ... M8: =L8*(1+Assumptions!$B$3)
A9: Canada | B9: 280 | C9: =B9*(1+Assumptions!$B$3) | D9: =C9*(1+Assumptions!$B$3) | E9: =D9*(1+Assumptions!$B$3) | F9: =E9*(1+Assumptions!$B$3) | G9: =F9*(1+Assumptions!$B$3) | H9: =G9*(1+Assumptions!$B$3) | I9: =H9*(1+Assumptions!$B$3) | J9: =I9*(1+Assumptions!$B$3) | ... M9: =L9*(1+Assumptions!$B$3)

Sheet Revenue
A1: Region | B1: Jan | C1: Feb | D1: Mar | E1: Apr | F1: May | G1: Jun | H1: Jul | I1: Aug | J1: Sep | K1: Oct | L1: Nov | M1: Dec
A2: Americas | B2: =Regions!$B$2*Assumptions!$B$2 | C2: =Regions!$C$2*Assumptions!$B$2 | D2: =Regions!$D$2*Assumptions!$B$2 | E2: =Regions!$E$2*Assumptions!$B$2 | F2: =Regions!$F$2*Assumptions!$B$2 | G2: =Regions!$G$2*Assumptions!$B$2 | H2: =Regions!$H$2*Assumptions!$B$2 | I2: =Regions!$I$2*Assumptions!$B$2 | J2: =Regions!$J$2*Assumptions!$B$2 | K2: =Regions!$K$2*Assumptions!$B$2 | L2: =Regions!$L$2*Assumptions!$B$2 | M2: =Regions!$M$2*Assumptions!$B$2
A3: EMEA | B3: =Regions!$B$3*Assumptions!$B$2 | C3: =Regions!$C$3*Assumptions!$B$2 | D3: =Regions!$D$3*Assumptions!$B$2 | E3: =Regions!$E$3*Assumptions!$B$2 | F3: =Regions!$F$3*Assumptions!$B$2 | G3: =Regions!$G$3*Assumptions!$B$2 | H3: =Regions!$H$3*Assumptions!$B$2 | I3: =Regions!$I$3*Assumptions!$B$2 | J3: =Regions!$J$3*Assumptions!$B$2 | K3: =Regions!$K$3*Assumptions!$B$2 | L3: =Regions!$L$3*Assumptions!$B$2 | M3: =Regions!$M$3*Assumptions!$B$2
A4: APAC | B4: =Regions!$B$4*Assumptions!$B$2 | C4: =Regions!$C$4*Assumptions!$B$2 | D4: =Regions!$D$4*Assumptions!$B$2 | E4: =Regions!$E$4*Assumptions!$B$2 | F4: =Regions!$F$4*Assumptions!$B$2 | G4: =Regions!$G$4*Assumptions!$B$2 | H4: =Regions!$H$4*Assumptions!$B$2 | I4: =Regions!$I$4*Assumptions!$B$2 | J4: =Regions!$J$4*Assumptions!$B$2 | K4: =Regions!$K$4*Assumptions!$B$2 | L4: =Regions!$L$4*Assumptions!$B$2 | M4: =Regions!$M$4*Assumptions!$B$2
A5: LATAM | B5: =Regions!$B$5*Assumptions!$B$2 | C5: =Regions!$C$5*Assumptions!$B$2 | D5: =Regions!$D$5*Assumptions!$B$2 | E5: =Regions!$E$5*Assumptions!$B$2 | F5: =Regions!$F$5*Assumptions!$B$2 | G5: =Regions!$G$5*Assumptions!$B$2 | H5: =Regions!$H$5*Assumptions!$B$2 | I5: =Regions!$I$5*Assumptions!$B$2 | J5: =Regions!$J$5*Assumptions!$B$2 | K5: =Regions!$K$5*Assumptions!$B$2 | L5: =Regions!$L$5*Assumptions!$B$2 | M5: =Regions!$M$5*Assumptions!$B$2
A6: ANZ | B6: =Regions!$B$6*Assumptions!$B$2 | C6: =Regions!$C$6*Assumptions!$B$2 | D6: =Regions!$D$6*Assumptions!$B$2 | E6: =Regions!$E$6*Assumptions!$B$2 | F6: =Regions!$F$6*Assumptions!$B$2 | G6: =Regions!$G$6*Assumptions!$B$2 | H6: =Regions!$H$6*Assumptions!$B$2 | I6: =Regions!$I$6*Assumptions!$B$2 | J6: =Regions!$J$6*Assumptions!$B$2 | K6: =Regions!$K$6*Assumptions!$B$2 | L6: =Regions!$L$6*Assumptions!$B$2 | M6: =Regions!$M$6*Assumptions!$B$2
A7: India | B7: =Regions!$B$7*Assumptions!$B$2 | C7: =Regions!$C$7*Assumptions!$B$2 | D7: =Regions!$D$7*Assumptions!$B$2 | E7: =Regions!$E$7*Assumptions!$B$2 | F7: =Regions!$F$7*Assumptions!$B$2 | G7: =Regions!$G$7*Assumptions!$B$2 | H7: =Regions!$H$7*Assumptions!$B$2 | I7: =Regions!$I$7*Assumptions!$B$2 | J7: =Regions!$J$7*Assumptions!$B$2 | K7: =Regions!$K$7*Assumptions!$B$2 | L7: =Regions!$L$7*Assumptions!$B$2 | M7: =Regions!$M$7*Assumptions!$B$2
A8: Japan | B8: =Regions!$B$8*Assumptions!$B$2 | C8: =Regions!$C$8*Assumptions!$B$2 | D8: =Regions!$D$8*Assumptions!$B$2 | E8: =Regions!$E$8*Assumptions!$B$2 | F8: =Regions!$F$8*Assumptions!$B$2 | G8: =Regions!$G$8*Assumptions!$B$2 | H8: =Regions!$H$8*Assumptions!$B$2 | I8: =Regions!$I$8*Assumptions!$B$2 | J8: =Regions!$J$8*Assumptions!$B$2 | K8: =Regions!$K$8*Assumptions!$B$2 | L8: =Regions!$L$8*Assumptions!$B$2 | M8: =Regions!$M$8*Assumptions!$B$2
A9: Canada | B9: =Regions!$B$9*Assumptions!$B$2 | C9: =Regions!$C$9*Assumptions!$B$2 | D9: =Regions!$D$9*Assumptions!$B$2 | E9: =Regions!$E$9*Assumptions!$B$2 | F9: =Regions!$F$9*Assumptions!$B$2 | G9: =Regions!$G$9*Assumptions!$B$2 | H9: =Regions!$H$9*Assumptions!$B$2 | I9: =Regions!$I$9*Assumptions!$B$2 | J9: =Regions!$J$9*Assumptions!$B$2 | K9: =Regions!$K$9*Assumptions!$B$2 | L9: =Regions!$L$9*Assumptions!$B$2 | M9: =Regions!$M$9*Assumptions!$B$2

Sheet Income
A1: Line Item | B1: Jan | C1: Feb | D1: Mar | E1: Apr | F1: May | G1: Jun | H1: Jul | I1: Aug | J1: Sep | K1: Oct | L1: Nov | M1: Dec | N1: FY Total
A2: Revenue | B2: =SUM(Revenue!$B$2:$B$9) | C2: =SUM(Revenue!$C$2:$C$9) | D2: =SUM(Revenue!$D$2:$D$9) | E2: =SUM(Revenue!$E$2:$E$9) | F2: =SUM(Revenue!$F$2:$F$9) | G2: =SUM(Revenue!$G$2:$G$9) | H2: =SUM(Revenue!$H$2:$H$9) | I2: =SUM(Revenue!$I$2:$I$9) | J2: =SUM(Revenue!$J$2:$J$9) | K2: =SUM(Revenue!$K$2:$K$9) | L2: =SUM(Revenue!$L$2:$L$9) | M2: =SUM(Revenue!$M$2:$M$9) | N2: =SUM($B$2:$M$2)
A3: COGS | B3: =$B$2*Assumptions!$B$5 | C3: =$C$2*Assumptions!$B$5 | D3: =$D$2*Assumptions!$B$5 | E3: =$E$2*Assumptions!$B$5 | F3: =$F$2*Assumptions!$B$5 | G3: =$G$2*Assumptions!$B$5 | H3: =$H$2*Assumptions!$B$5 | I3: =$I$2*Assumptions!$B$5 | J3: =$J$2*Assumptions!$B$5 | K3: =$K$2*Assumptions!$B$5 | L3: =$L$2*Assumptions!$B$5 | M3: =$M$2*Assumptions!$B$5 | N3: =SUM($B$3:$M$3)
A4: Gross Profit | B4: =$B$2-$B$3 | C4: =$C$2-$C$3 | D4: =$D$2-$D$3 | E4: =$E$2-$E$3 | F4: =$F$2-$F$3 | G4: =$G$2-$G$3 | H4: =$H$2-$H$3 | I4: =$I$2-$I$3 | J4: =$J$2-$J$3 | K4: =$K$2-$K$3 | L4: =$L$2-$L$3 | M4: =$M$2-$M$3 | N4: =SUM($B$4:$M$4)
A5: OpEx | B5: =Assumptions!$B$6 | C5: =Assumptions!$B$6 | D5: =Assumptions!$B$6 | E5: =Assumptions!$B$6 | F5: =Assumptions!$B$6 | G5: =Assumptions!$B$6 | H5: =Assumptions!$B$6 | I5: =Assumptions!$B$6 | ... M5: =Assumptions!$B$6 | N5: =SUM($B$5:$M$5)
A6: EBT | B6: =$B$4-$B$5 | C6: =$C$4-$C$5 | D6: =$D$4-$D$5 | E6: =$E$4-$E$5 | F6: =$F$4-$F$5 | G6: =$G$4-$G$5 | H6: =$H$4-$H$5 | I6: =$I$4-$I$5 | J6: =$J$4-$J$5 | K6: =$K$4-$K$5 | L6: =$L$4-$L$5 | M6: =$M$4-$M$5 | N6: =SUM($B$6:$M$6)
A7: Tax | B7: =MAX(0,$B$6)*Assumptions!$B$7 | C7: =MAX(0,$C$6)*Assumptions!$B$7 | D7: =MAX(0,$D$6)*Assumptions!$B$7 | E7: =MAX(0,$E$6)*Assumptions!$B$7 | F7: =MAX(0,$F$6)*Assumptions!$B$7 | G7: =MAX(0,$G$6)*Assumptions!$B$7 | H7: =MAX(0,$H$6)*Assumptions!$B$7 | I7: =MAX(0,$I$6)*Assumptions!$B$7 | J7: =MAX(0,$J$6)*Assumptions!$B$7 | K7: =MAX(0,$K$6)*Assumptions!$B$7 | L7: =MAX(0,$L$6)*Assumptions!$B$7 | M7: =MAX(0,$M$6)*Assumptions!$B$7 | N7: =SUM($B$7:$M$7)
A8: Net Income | B8: =$B$6-$B$7 | C8: =$C$6-$C$7 | D8: =$D$6-$D$7 | E8: =$E$6-$E$7 | F8: =$F$6-$F$7 | G8: =$G$6-$G$7 | H8: =$H$6-$H$7 | I8: =$I$6-$I$7 | J8: =$J$6-$J$7 | K8: =$K$6-$K$7 | L8: =$L$6-$L$7 | M8: =$M$6-$M$7 | N8: =SUM($B$8:$M$8)

Sheet Board
A1: KPI | B1: Value
A2: ARR | B2: =Income!$M$2*12
A3: MRR | B3: =Income!$M$2
A4: FY Revenue | B4: =Income!$N$2
A5: Gross Margin | B5: =IF(Income!$N$2=0,0,Income!$N$4/Income!$N$2)
A6: FY Net Income | B6: =Income!$N$8
A7: List Price | B7: =Assumptions!$B$2
A25: Month | B25: Jan | C25: Feb | D25: Mar | E25: Apr | F25: May | G25: Jun | H25: Jul | I25: Aug | J25: Sep | K25: Oct | L25: Nov | M25: Dec
A26: Revenue | B26: =Income!$B$2 | C26: =Income!$C$2 | D26: =Income!$D$2 | E26: =Income!$E$2 | F26: =Income!$F$2 | G26: =Income!$G$2 | H26: =Income!$H$2 | I26: =Income!$I$2 | J26: =Income!$J$2 | K26: =Income!$K$2 | L26: =Income!$L$2 | M26: =Income!$M$2
A28: Board pack — chart is preserve-only in the Dotall demo
